scrobblez/__init__.py
scrobblez/__main__.py
scrobblez/cli.py
scrobblez/looper.py
scrobblez/scrobblers.py
scrobblez/types.py
scrobblez/metadata_filter/__init__.py
scrobblez-0.1.1.dist-info/LICENSE
scrobblez-0.1.1.dist-info/METADATA
scrobblez-0.1.1.dist-info/WHEEL
scrobblez-0.1.1.dist-info/entry_points.txt
scrobblez-0.1.1.dist-info/top_level.txt
scrobblez-0.1.1.dist-info/RECORD
