Metadata-Version: 2.1
Name: scrobblez
Version: 0.1.1
Summary: Scrobbler for MPRIS 2 compatible clients
Home-page: https://github.com/YodaEmbedding/scrobblez
Author: Mateen Ulhaq
Author-email: mulhaq2005@gmail.com
License: MIT
License-File: LICENSE
Requires-Dist: metadata-filter
Requires-Dist: mpris2
Requires-Dist: pylast
Requires-Dist: pyxdg
